my_modgun_44/__init__.py
my_modgun_44/core.py
my_modgun_44-0.3.0.dist-info/METADATA
my_modgun_44-0.3.0.dist-info/WHEEL
my_modgun_44-0.3.0.dist-info/top_level.txt
my_modgun_44-0.3.0.dist-info/RECORD
