Metadata-Version: 2.4
Name: my_modgun_44
Version: 0.3.0
Summary: My custom text module
Requires-Python: >=3.6
Dynamic: requires-python
Dynamic: summary
